{
    "17545119": {
        "podId": "17545119",
        "type": "0",
        "cclass": 0,
        "value": "100",
        "category": null,
        "image": {
            "url": "http:\/\/cdn.cpnscdn.com\/insight.coupons.com\/COS20\/_Cache\/_ImageCache\/119\/17545119.gif",
            "height": "100",
            "width": "80"
        },
        "burstText": "",
        "summary": "SAVE $1.00",
        "brand": "Glade\u00ae",
        "link_text": "",
        "link_url": "",
        "activated": "2012-09-10T00:01:00",
        "expiration": "2012-11-21T23:59:00",
        "isuff": "119\/17545119.gif",
        "imagePrefix": null,
        "details": "on any Glade\u00ae PlugIns\u00ae Scented Oil warmer or starter kit",
        "catid": "340",
        "catdesc": "Air, Rug & Fabric Care",
        "slot": "0",
        "prodinfo": "on any Glade\u00ae PlugIns\u00ae Scented Oil warmer or starter kit",
        "cpnuse": "1",
        "printed": null,
        "actiontaken": null,
        "printCount": null,
        "onCard": null,
        "sid": "13134963",
        "fid": "04410155",
        "videoURL": "",
        "catlevel1": "105",
        "catlevel2": "304",
        "catlevel3": "340",
        "catdesc1": "Household",
        "catdesc2": "Household Cleaners\/ Supplies",
        "catdesc3": "Air, Rug & Fabric Care",
        "restricted": 0
    },
    "17545197": {
        "podId": "17545197",
        "type": "0",
        "cclass": 0,
        "value": "150",
        "category": null,
        "image": {
            "url": "http:\/\/cdn.cpnscdn.com\/insight.coupons.com\/COS20\/_Cache\/_ImageCache\/197\/17545197.gif",
            "height": "100",
            "width": "80"
        },
        "burstText": "",
        "summary": "SAVE $1.50",
        "brand": "Glade\u00ae",
        "link_text": "",
        "link_url": "",
        "activated": "2012-09-10T00:01:00",
        "expiration": "2012-11-21T23:59:00",
        "isuff": "197\/17545197.gif",
        "imagePrefix": null,
        "details": "on any TWO Glade\u00ae 4 oz. Jar Candles",
        "catid": "340",
        "catdesc": "Air, Rug & Fabric Care",
        "slot": "0",
        "prodinfo": "on any TWO Glade\u00ae 4 oz. Jar Candles",
        "cpnuse": "1",
        "printed": null,
        "actiontaken": null,
        "printCount": null,
        "onCard": null,
        "sid": "07758053",
        "fid": "09787143",
        "videoURL": "",
        "catlevel1": "105",
        "catlevel2": "304",
        "catlevel3": "340",
        "catdesc1": "Household",
        "catdesc2": "Household Cleaners\/ Supplies",
        "catdesc3": "Air, Rug & Fabric Care",
        "restricted": 0
    },
    "17545363": {
        "podId": "17545363",
        "type": "0",
        "cclass": 0,
        "value": "100",
        "category": null,
        "image": {
            "url": "http:\/\/cdn.cpnscdn.com\/insight.coupons.com\/COS20\/_Cache\/_ImageCache\/363\/17545363.gif",
            "height": "100",
            "width": "80"
        },
        "burstText": "",
        "summary": "SAVE $1.00",
        "brand": "Glade\u00ae",
        "link_text": "",
        "link_url": "",
        "activated": "2012-09-10T00:01:00",
        "expiration": "2012-11-21T23:59:00",
        "isuff": "363\/17545363.gif",
        "imagePrefix": null,
        "details": "on any TWO Glade\u00ae Sense & Spray\u00ae refills",
        "catid": "340",
        "catdesc": "Air, Rug & Fabric Care",
        "slot": "0",
        "prodinfo": "on any TWO Glade\u00ae Sense & Spray\u00ae refills",
        "cpnuse": "1",
        "printed": null,
        "actiontaken": null,
        "printCount": null,
        "onCard": null,
        "sid": "09743433",
        "fid": "07801929",
        "videoURL": "",
        "catlevel1": "105",
        "catlevel2": "304",
        "catlevel3": "340",
        "catdesc1": "Household",
        "catdesc2": "Household Cleaners\/ Supplies",
        "catdesc3": "Air, Rug & Fabric Care",
        "restricted": 0
    },
    "17545362": {
        "podId": "17545362",
        "type": "0",
        "cclass": 0,
        "value": "100",
        "category": null,
        "image": {
            "url": "http:\/\/cdn.cpnscdn.com\/insight.coupons.com\/COS20\/_Cache\/_ImageCache\/362\/17545362.gif",
            "height": "100",
            "width": "80"
        },
        "burstText": "",
        "summary": "SAVE $1.00",
        "brand": "Glade\u00ae",
        "link_text": "",
        "link_url": "",
        "activated": "2012-09-10T00:01:00",
        "expiration": "2012-11-21T23:59:00",
        "isuff": "362\/17545362.gif",
        "imagePrefix": null,
        "details": "on any Glade\u00ae D\u00e9cor Scents\u00ae holder or TWO refills",
        "catid": "340",
        "catdesc": "Air, Rug & Fabric Care",
        "slot": "0",
        "prodinfo": "on any Glade\u00ae D\u00e9cor Scents\u00ae holder or TWO refills",
        "cpnuse": "1",
        "printed": null,
        "actiontaken": null,
        "printCount": null,
        "onCard": null,
        "sid": "09535011",
        "fid": "08010350",
        "videoURL": "",
        "catlevel1": "105",
        "catlevel2": "304",
        "catlevel3": "340",
        "catdesc1": "Household",
        "catdesc2": "Household Cleaners\/ Supplies",
        "catdesc3": "Air, Rug & Fabric Care",
        "restricted": 0
    }
}